{"downloaded": true, "htmlmade": false, "id": "39360466", "source": "MED", "pmid": "39360466", "pmcid": "PMC11754993", "fullTextIdList": {"fullTextId": "PMC11754993"}, "doi": "10.1111/bioe.13356", "title": "Addressing the COVID-induced healthcare backlog: How can we balance the interests of people and nature?", "authorString": "Pratt B.", "authorList": {"author": {"fullName": "Pratt B", "firstName": "Bridget", "lastName": "Pratt", "initials": "B", "authorId": {"@type": "ORCID", "#text": "0000-0002-4934-3560"}, "authorAffiliationDetailsList": {"authorAffiliation": [{"affiliation": "Queensland Bioethics Centre, Australian Catholic University, Brisbane, Queensland, Australia."}, {"affiliation": "School of Population and Global Health, University of Melbourne, Melbourne, Victoria, Australia."}]}}}, "authorIdList": {"authorId": {"@type": "ORCID", "#text": "0000-0002-4934-3560"}}, "journalInfo": {"issue": "2", "volume": "39", "journalIssueId": "3890625", "dateOfPublication": "2025 Feb", "monthOfPublication": "2", "yearOfPublication": "2025", "printPublicationDate": "2025-02-01", "journal": {"title": "Bioethics", "ISOAbbreviation": "Bioethics", "medlineAbbreviation": "Bioethics", "NLMid": "8704792", "ISSN": "0269-9702", "ESSN": "1467-8519"}}, "pubYear": "2025", "pageInfo": "195-204", "abstractText": "The COVID-19 pandemic created healthcare backlogs of routine primary and preventive care, elective procedures, dental care, and mental healthcare appointments across the world. So far, governments are responding by enacting pandemic recovery policies that expand their healthcare sector activity, without much, if any, consideration of its effects on the environmental crisis that is (among other things) worsening human health and health equity. This paper argues that, as a matter of health and social justice, governments have an ethical responsibility to equitably reduce the backlog with minimal environmental damage. To do so, a first key action is to give priority to policy options that minimise negative human impacts on the environment. Yet these policies alone will not be sufficient to address the backlog, particularly in relation to elective procedures. The paper therefore contends that a second key action for governments is to enact the policy options that are best able to equitably reduce the remainder of the backlog, while accelerating the transition to sustainable health care in ways that are best able to reduce the specific environmental costs of those policy options. It concludes by considering whether limits apply to governments' ethical responsibilities that ultimately mean accelerating the transition to sustainable health care is not required when addressing the backlog.", "affiliation": "Queensland Bioethics Centre, Australian Catholic University, Brisbane, Queensland, Australia.", "publicationStatus": "ppublish", "language": "eng", "pubModel": "Print-Electronic", "pubTypeList": {"pubType": ["research-article", "Journal Article"]}, "grantsList": {"grant": {"agency": "Mater Misericordiae Ltd", "orderIn": "0"}}, "meshHeadingList": {"meshHeading": [{"majorTopic_YN": "N", "descriptorName": "Humans"}, {"majorTopic_YN": "Y", "descriptorName": "Social Justice"}, {"majorTopic_YN": "Y", "descriptorName": "Health Policy"}, {"majorTopic_YN": "Y", "descriptorName": "Delivery of Health Care", "meshQualifierList": {"meshQualifier": {"abbreviation": "ES", "qualifierName": "ethics", "majorTopic_YN": "N"}}}, {"majorTopic_YN": "Y", "descriptorName": "Pandemics"}, {"majorTopic_YN": "Y", "descriptorName": "Health Equity", "meshQualifierList": {"meshQualifier": {"abbreviation": "ES", "qualifierName": "ethics", "majorTopic_YN": "N"}}}, {"majorTopic_YN": "Y", "descriptorName": "COVID-19", "meshQualifierList": {"meshQualifier": {"abbreviation": "EP", "qualifierName": "epidemiology", "majorTopic_YN": "N"}}}, {"majorTopic_YN": "N", "descriptorName": "SARS-CoV-2"}]}, "keywordList": {"keyword": ["Environment", "Ethics", "Health care", "Justice", "Covid\u201019"]}, "subsetList": {"subset": {"code": "IM", "name": "Index Medicus"}}, "fullTextUrlList": {"fullTextUrl": [{"availability": "Subscription required", "availabilityCode": "S", "documentStyle": "doi", "site": "DOI", "url": "https://doi.org/10.1111/bioe.13356"}, {"availability": "Open access", "availabilityCode": "OA", "documentStyle": "html", "site": "Europe_PMC", "url": "https://europepmc.org/articles/PMC11754993"}, {"availability": "Open access", "availabilityCode": "OA", "documentStyle": "pdf", "site": "Europe_PMC", "url": "https://europepmc.org/articles/PMC11754993?pdf=render"}]}, "isOpenAccess": "Y", "inEPMC": "Y", "inPMC": "Y", "hasPDF": "Y", "hasBook": "N", "hasSuppl": "N", "citedByCount": "1", "hasData": "N", "hasReferences": "Y", "hasTextMinedTerms": "Y", "hasDbCrossReferences": "N", "hasLabsLinks": "N", "license": "cc by-nc-nd", "hasEvaluations": "N", "authMan": "N", "epmcAuthMan": "N", "nihAuthMan": "N", "hasTMAccessionNumbers": "N", "dateOfCompletion": "2025-04-24", "dateOfCreation": "2024-10-03", "firstIndexDate": "2024-10-03", "fullTextReceivedDate": "2025-01-27", "dateOfRevision": "2025-04-24", "electronicPublicationDate": "2024-10-03", "firstPublicationDate": "2024-10-03"}